gitzilla
