Metadata-Version: 1.1
Name: gitzilla
Version: 1.9.1
Summary: Git-Bugzilla integration
Home-page: http://www.theoldmonk.net/gitzilla/
Author: Devendra Gera
Author-email: gera@theoldmonk.net
License: UNKNOWN
Platform: UNKNOWN
Requires: pybugz
